Metadata-Version: 2.1
Name: pattern-singleton
Version: 1.2.0
Summary: Metaclass Singleton Pattern (supports Multi-thread).
Home-page: https://github.com/MarcinMysliwiec/pattern_singleton
Author: Marcin Mysliwiec
Author-email: marcin.mysliw@gmail.com
License: MIT license
Keywords: pattern_singleton,singleton,design,pattern,metaclass,multi-thread
Platform: UNKNOWN
Classifier: Development Status :: 4 - Beta
Classifier: Intended Audience :: Developers
Classifier: License :: OSI Approved :: MIT License
Classifier: Natural Language :: English
Classifier: Programming Language :: Python :: 3
Classifier: Programming Language :: Python :: 3.6
Classifier: Programming Language :: Python :: 3.7
Classifier: Programming Language :: Python :: 3.8
Requires-Python: >=3.6
